sentry_qiwei/__init__.py
sentry_qiwei/forms.py
sentry_qiwei/plugin.py
sentry_qiwei-1.0.5.dist-info/LICENSE
sentry_qiwei-1.0.5.dist-info/METADATA
sentry_qiwei-1.0.5.dist-info/WHEEL
sentry_qiwei-1.0.5.dist-info/entry_points.txt
sentry_qiwei-1.0.5.dist-info/top_level.txt
sentry_qiwei-1.0.5.dist-info/RECORD
