Metadata-Version: 2.1
Name: sentry-qiwei
Version: 1.0.5
Summary: sentry extension which can send error to qiwei.
Home-page: https://github.com/snakeliwei/sentry_qiwei
Author: snakeliwei
Author-email: snakeliwei@gmail.com
License: GNU
Keywords: sentry qiwei
Classifier: Framework :: Django
Classifier: Intended Audience :: Developers
Classifier: Operating System :: OS Independent
Classifier: Natural Language :: Chinese (Simplified)
Classifier: Programming Language :: Python :: 2.7
Classifier: License :: OSI Approved :: GNU General Public License v3 (GPLv3)
License-File: LICENSE
Requires-Dist: sentry
Requires-Dist: requests
Requires-Dist: Django
